dongsam/__init__.py
dongsam/basic/__init__.py
dongsam/basic/struct.py
dongsam-0.1.dist-info/LICENSE
dongsam-0.1.dist-info/METADATA
dongsam-0.1.dist-info/WHEEL
dongsam-0.1.dist-info/top_level.txt
dongsam-0.1.dist-info/RECORD
